emr_serverless_sql/__init__.py
emr_serverless_sql/emr_serverless.py
emr_serverless_sql/emrss_cli.py
emr_serverless_sql/sql_template.py
emr_serverless_sql_cli-0.5.0.dist-info/LICENSE
emr_serverless_sql_cli-0.5.0.dist-info/METADATA
emr_serverless_sql_cli-0.5.0.dist-info/WHEEL
emr_serverless_sql_cli-0.5.0.dist-info/entry_points.txt
emr_serverless_sql_cli-0.5.0.dist-info/RECORD
