Metadata-Version: 2.1
Name: emr-serverless-sql-cli
Version: 0.5.0
Summary: 
Author: Damon P. Cortesi
Author-email: 1512+dacort@users.noreply.github.com
Requires-Python: >=3.10,<4.0
Classifier: Programming Language :: Python :: 3
Classifier: Programming Language :: Python :: 3.10
Classifier: Programming Language :: Python :: 3.11
Requires-Dist: boto3 (>=1.26.57,<2.0.0)
Requires-Dist: click (>=8.1.3,<9.0.0)
Requires-Dist: nbconvert (>=7.8.0,<8.0.0)
